{
  "fields": [],
  "generated_doNotEdit": {
    "title": "ConstantIntProvider",
    "description": "Specifies a constant integer",
    "fields": [
      {
        "id": "type",
        "title": "enum SharedTypes_v1_21_20_IntProviderType",
        "description": "enum SharedTypes_v1_21_20_IntProviderType",
        "dataType": 2
      },
      {
        "id": "value",
        "title": "value",
        "description": "Constant value",
        "dataType": 0
      }
    ]
  },
  "generatedFromSchema_doNotEdit": {
    "id": "ConstantIntProvider",
    "title": "ConstantIntProvider Misc",
    "description": "Specifies a constant integer",
    "fields": [
      {
        "id": "type",
        "title": "IntProviderType",
        "dataType": 2,
        "isRequired": true
      },
      {
        "id": "value",
        "title": "Value",
        "description": "Constant value",
        "dataType": 0,
        "isRequired": true
      }
    ]
  }
}