{
  "$schema": "../../../schemas/dataform/form-definition.schema.json",
  "summarizer": {
    "phrases": [
      {
        "tokens": [
          {
            "type": "literal",
            "text": "defines behavior.sonic boom configuration"
          }
        ]
      }
    ]
  },
  "id": "minecraft:behavior.sonic_boom",
  "fields": [],
  "generatedFromSchema_doNotEdit": {
    "id": "minecraft:behavior.sonic_boom",
    "title": "Minecraft Behavior.sonic Boom Misc",
    "description": "Allows this entity to perform a 'sonic boom' ranged attack",
    "fields": [
      {
        "id": "attack_cooldown",
        "title": "Attack Cooldown",
        "description": "Cooldown in seconds required after using this attack until the entity can use sonic boom again. Default value: 5.",
        "dataType": 3
      },
      {
        "id": "attack_damage",
        "title": "Attack Damage",
        "description": "Attack damage of the sonic boom. Default value: 30.",
        "dataType": 3
      },
      {
        "id": "attack_range_horizontal",
        "title": "Attack Range Horizontal",
        "description": "Horizontal range (in blocks) at which the sonic boom can damage the target. Default value: 15.",
        "dataType": 3
      },
      {
        "id": "attack_range_vertical",
        "title": "Attack Range Vertical",
        "description": "Vertical range (in blocks) at which the sonic boom can damage the target. Default value: 20.",
        "dataType": 3
      },
      {
        "id": "attack_sound",
        "title": "Attack Sound",
        "description": "Sound event for the attack.",
        "dataType": 2
      },
      {
        "id": "charge_sound",
        "title": "Charge Sound",
        "description": "Sound event for the charge up.",
        "dataType": 2
      },
      {
        "id": "control_flags",
        "title": "Control Flags",
        "dataType": 17
      },
      {
        "id": "duration",
        "title": "Duration",
        "description": "Goal duration in seconds Default value: 0.",
        "dataType": 3
      },
      {
        "id": "duration_until_attack_sound",
        "title": "Duration Until Attack Sound",
        "description": "Duration in seconds until the attack sound is played. Default value: 1.7.",
        "dataType": 3
      },
      {
        "id": "knockback_height_cap",
        "title": "Knockback Height Cap",
        "description": "Height cap of the attack knockback's vertical delta. Default value: 0.",
        "dataType": 3
      },
      {
        "id": "knockback_horizontal_strength",
        "title": "Knockback Horizontal Strength",
        "description": "Horizontal strength of the attack's knockback applied to the attack target. Default value: 0.",
        "dataType": 3
      },
      {
        "id": "knockback_vertical_strength",
        "title": "Knockback Vertical Strength",
        "description": "Vertical strength of the attack's knockback applied to the attack target. Default value: 0.",
        "dataType": 3
      },
      {
        "id": "priority",
        "title": "Priority",
        "dataType": 0
      },
      {
        "id": "speed_multiplier",
        "title": "Speed Multiplier",
        "description": "This multiplier modifies the attacking entity's speed when moving toward the target. Default value: 1.",
        "dataType": 3
      }
    ]
  }
}
