{
  "id": "WeightedRandomItem",
  "fields": [],
  "generatedFromSchema_doNotEdit": {
    "id": "WeightedRandomItem",
    "title": "WeightedRandomItem Misc",
    "description": "Weighted Random Item",
    "fields": [
      {
        "id": "data",
        "title": "Data",
        "description": "Item's data",
        "dataType": 17,
        "isRequired": true
      },
      {
        "id": "weight",
        "title": "Weight",
        "description": "Weight of item",
        "dataType": 0,
        "isRequired": true
      }
    ]
  }
}