{
  "id": "Actor Document",
  "fields": [],
  "generatedFromSchema_doNotEdit": {
    "id": "Actor Document",
    "title": "Actor Document Entity",
    "fields": [
      {
        "id": "component_groups",
        "title": "Component Groups",
        "dataType": 16,
        "subFormId": "entity/entity_component_definitions"
      },
      {
        "id": "components",
        "title": "Components",
        "dataType": 16,
        "subFormId": "entity/entity_component_definitions"
      },
      {
        "id": "description",
        "title": "Description",
        "description": "Dynamic value",
        "dataType": 16,
        "isRequired": true
      },
      {
        "id": "events",
        "title": "Events",
        "description": "Dynamic value",
        "dataType": 16
      }
    ]
  }
}