{
  "$schema": "../../../schemas/dataform/form-definition.schema.json",
  "summarizer": {
    "phrases": [
      {
        "tokens": [
          {
            "type": "literal",
            "text": "has custom armor equipment slot mapping"
          }
        ]
      }
    ]
  },
  "fields": [],
  "generated_doNotEdit": {
    "id": "minecraft:entity_armor_equipment_slot_mapping",
    "title": "Entity Armor Equipment Slot Mapping",
    "description": "It defines to which armor slot an item equipped to 'minecraft:equippable''s second slot should be equipped to. It is automatically applied to all entities for worlds with a version greater than or equal to 1.21.10. For older worlds, 'slot.armor.torso' will be used. It is strongly advised not to explicitly use this component, as no backwards compatibility for it will be provided.",
    "fields": [
      {
        "id": "armor_slot",
        "title": "Armor Slot",
        "description": "The armor slot an item equipped to 'minecraft:equippable''s second slot should be equipped to. It defaults to 'slot.armor.torso' for entities with a format version prior to 1.21.10, and to 'slot.armor.body' otherwise.",
        "dataType": 2
      }
    ]
  }
}