{
  "$schema": "../../../schemas/dataform/form-definition.schema.json",
  "id": "block_reference",
  "title": "Block Reference (v1.10.0)",
  "description": "Defines a block reference object as used by resource pack client definitions (format_version 1.10.0).",
  "summarizer": {
    "phrases": [
      {
        "tokens": [
          {
            "type": "literal",
            "text": "references a block by name and its state values"
          }
        ]
      }
    ]
  },
  "fields": [],
  "generated_doNotEdit": {
    "id": "block_reference",
    "fields": [
      {
        "dataType": 2,
        "id": "name",
        "title": "Name",
        "isRequired": true
      },
      {
        "dataType": 16,
        "id": "states",
        "title": "States",
        "isRequired": true,
        "subForm": {
          "fields": [
            {
              "dataType": 0,
              "id": "\\w*:?\\w+",
              "title": "\\w* ?\\w+",
              "isRequired": false,
              "alternates": [
                {
                  "dataType": 1,
                  "id": "\\w*:?\\w+",
                  "isRequired": false
                },
                {
                  "dataType": 2,
                  "id": "\\w*:?\\w+",
                  "isRequired": false
                }
              ]
            }
          ]
        }
      }
    ],
    "dataVersion": "1.10.0"
  }
}